<?xml version="1.0" encoding="utf-8"?>
<bindings xmlns="http://java.sun.com/xml/ns/jaxb" xmlns:xs="http://www.w3.org/2001/XMLSchema" version="2.1">
  <bindings schemaLocation="https://campaign.api.sandbox.bingads.microsoft.com/Api/Advertiser/CampaignManagement/V11/CampaignManagementService.svc?xsd=xsd1">
    <bindings node="//xs:simpleType[@name='CampaignType']">
      <javaType name="java.util.Collection&lt;CampaignType&gt;" parseMethod="com.microsoft.bingads.v11.campaignmanagement.CampaignTypeConverter.convertToList" printMethod="com.microsoft.bingads.v11.campaignmanagement.CampaignTypeConverter.convertToString" />
    </bindings>
    <bindings node="//xs:simpleType[@name='AdDistribution']">
      <javaType name="java.util.Collection&lt;AdDistribution&gt;" parseMethod="com.microsoft.bingads.v11.campaignmanagement.AdDistributionConverter.convertToList" printMethod="com.microsoft.bingads.v11.campaignmanagement.AdDistributionConverter.convertToString" />
    </bindings>
    <bindings node="//xs:simpleType[@name='AdGroupAdditionalField']">
      <javaType name="java.util.Collection&lt;AdGroupAdditionalField&gt;" parseMethod="com.microsoft.bingads.v11.campaignmanagement.AdGroupAdditionalFieldConverter.convertToList" printMethod="com.microsoft.bingads.v11.campaignmanagement.AdGroupAdditionalFieldConverter.convertToString" />
    </bindings>
    <bindings node="//xs:simpleType[@name='KeywordAdditionalField']">
      <javaType name="java.util.Collection&lt;KeywordAdditionalField&gt;" parseMethod="com.microsoft.bingads.v11.campaignmanagement.KeywordAdditionalFieldConverter.convertToList" printMethod="com.microsoft.bingads.v11.campaignmanagement.KeywordAdditionalFieldConverter.convertToString" />
    </bindings>
    <bindings node="//xs:simpleType[@name='AdExtensionsTypeFilter']">
      <javaType name="java.util.Collection&lt;AdExtensionsTypeFilter&gt;" parseMethod="com.microsoft.bingads.v11.campaignmanagement.AdExtensionsTypeFilterConverter.convertToList" printMethod="com.microsoft.bingads.v11.campaignmanagement.AdExtensionsTypeFilterConverter.convertToString" />
    </bindings>
    <bindings node="//xs:simpleType[@name='MediaEnabledEntityFilter']">
      <javaType name="java.util.Collection&lt;MediaEnabledEntityFilter&gt;" parseMethod="com.microsoft.bingads.v11.campaignmanagement.MediaEnabledEntityFilterConverter.convertToList" printMethod="com.microsoft.bingads.v11.campaignmanagement.MediaEnabledEntityFilterConverter.convertToString" />
    </bindings>
    <bindings node="//xs:simpleType[@name='AdGroupCriterionType']">
      <javaType name="java.util.Collection&lt;AdGroupCriterionType&gt;" parseMethod="com.microsoft.bingads.v11.campaignmanagement.AdGroupCriterionTypeConverter.convertToList" printMethod="com.microsoft.bingads.v11.campaignmanagement.AdGroupCriterionTypeConverter.convertToString" />
    </bindings>
    <bindings node="//xs:simpleType[@name='AudienceType']">
      <javaType name="java.util.Collection&lt;AudienceType&gt;" parseMethod="com.microsoft.bingads.v11.campaignmanagement.AudienceTypeConverter.convertToList" printMethod="com.microsoft.bingads.v11.campaignmanagement.AudienceTypeConverter.convertToString" />
    </bindings>
    <bindings node="//xs:simpleType[@name='ProfileType']">
      <javaType name="java.util.Collection&lt;ProfileType&gt;" parseMethod="com.microsoft.bingads.v11.campaignmanagement.ProfileTypeConverter.convertToList" printMethod="com.microsoft.bingads.v11.campaignmanagement.ProfileTypeConverter.convertToString" />
    </bindings>
    <bindings node="//xs:simpleType[@name='CampaignCriterionType']">
      <javaType name="java.util.Collection&lt;CampaignCriterionType&gt;" parseMethod="com.microsoft.bingads.v11.campaignmanagement.CampaignCriterionTypeConverter.convertToList" printMethod="com.microsoft.bingads.v11.campaignmanagement.CampaignCriterionTypeConverter.convertToString" />
    </bindings>
    <bindings node="//xs:simpleType[@name='AudienceAdditionalField']">
      <javaType name="java.util.Collection&lt;AudienceAdditionalField&gt;" parseMethod="com.microsoft.bingads.v11.campaignmanagement.AudienceAdditionalFieldConverter.convertToList" printMethod="com.microsoft.bingads.v11.campaignmanagement.AudienceAdditionalFieldConverter.convertToString" />
    </bindings>
    <bindings node="//xs:simpleType[@name='ConversionGoalType']">
      <javaType name="java.util.Collection&lt;ConversionGoalType&gt;" parseMethod="com.microsoft.bingads.v11.campaignmanagement.ConversionGoalTypeConverter.convertToList" printMethod="com.microsoft.bingads.v11.campaignmanagement.ConversionGoalTypeConverter.convertToString" />
    </bindings>
  </bindings>
</bindings>